libtgmk/__init__.py
libtgmk-0.4.5.dist-info/WHEEL
libtgmk-0.4.5.dist-info/METADATA
libtgmk-0.4.5.dist-info/RECORD
