Metadata-Version: 2.1
Name: libtgmk
Version: 0.4.5
Summary: LIBrary for TGMK (Tebi-Gibi-Mebi-Kibi), a 1024-base integer representation
Author-email: Carlo Alessandro Verre <carlo.alessandro.verre@gmail.com>
Requires-Python: >=3.6
Classifier: Programming Language :: Python :: 3
Classifier: Programming Language :: Python :: 3.6
Classifier: Development Status :: 4 - Beta
Classifier: Environment :: Console
Classifier: Intended Audience :: Developers
Classifier: License :: OSI Approved :: GNU General Public License v3 or later (GPLv3+)
Classifier: Operating System :: POSIX :: Linux
Project-URL: Home, https://pypi.org/project/libtgmk
